kevsight/__init__.py
kevsight/conf_sample.py
kevsight/config.py
kevsight/main.py
kevsight-0.1.2.dist-info/COPYING
kevsight-0.1.2.dist-info/METADATA
kevsight-0.1.2.dist-info/WHEEL
kevsight-0.1.2.dist-info/entry_points.txt
kevsight-0.1.2.dist-info/RECORD
