Metadata-Version: 2.3
Name: KEVSight
Version: 0.1.2
Summary: A client to generate sightings for Vulnerability-Lookup from the Known Exploited Vulnerabilities (KEV) catalog.
License: GPL-3.0-or-later
Keywords: Vulnerability-Lookup,Vulnerability,CVE,CISA,KEV
Author: Cédric Bonhomme
Author-email: cedric.bonhomme@circl.lu
Requires-Python: >=3.10,<4.0
Classifier: Development Status :: 5 - Production/Stable
Classifier: Environment :: Console
Classifier: Intended Audience :: Developers
Classifier: Intended Audience :: Science/Research
Classifier: License :: OSI Approved :: GNU General Public License v3 or later (GPLv3+)
Classifier: Operating System :: POSIX :: Linux
Classifier: Programming Language :: Python :: 3
Classifier: Programming Language :: Python :: 3.10
Classifier: Programming Language :: Python :: 3.11
Classifier: Programming Language :: Python :: 3.12
Classifier: Programming Language :: Python :: 3.13
Classifier: Topic :: Security
Requires-Dist: cisa-kev (>=2.0.2)
Requires-Dist: pyvulnerabilitylookup (>=2.5.0)
Project-URL: Homepage, https://github.com/vulnerability-lookup/KEVSight
Project-URL: Repository, https://github.com/vulnerability-lookup/KEVSight
